basic/__init__.py
basic/add.py
basic/determinant.py
extra/__init__.py
extra/dot.py
extra/multiply.py
pypacktut-0.4.7.dist-info/LICENSE
pypacktut-0.4.7.dist-info/METADATA
pypacktut-0.4.7.dist-info/WHEEL
pypacktut-0.4.7.dist-info/top_level.txt
pypacktut-0.4.7.dist-info/RECORD
